df_types/__init__.py
df_types/_codegen.py
df_types/_infer_types.py
df_types/_util.py
df_types/_version.py
df_types/config.py
df_types-0.0.2.dist-info/LICENSE
df_types-0.0.2.dist-info/METADATA
df_types-0.0.2.dist-info/WHEEL
df_types-0.0.2.dist-info/top_level.txt
df_types-0.0.2.dist-info/RECORD
