Metadata-Version: 2.1
Name: df-types
Version: 0.0.2
Summary: A tool for generating dataclass type files for pandas DataFrame rows
Home-page: https://github.com/jon-edward/df-types
Author: jon-edward
License: MIT
Keywords: python,pandas,dataclass,dataframe
Classifier: Intended Audience :: Developers
Classifier: License :: OSI Approved :: MIT License
Classifier: Programming Language :: Python :: 3
Classifier: Programming Language :: Python :: 3.10
Classifier: Operating System :: OS Independent
Requires: pandas
License-File: LICENSE
